<?xml version="1.0" encoding="utf-8"?>
<Votaciones xmlns:xsi="http://www.w3.org/2001/XMLSchema-instance" xmlns:xsd="http://www.w3.org/2001/XMLSchema" xmlns="http://tempuri.org/">
  <Votacion>
    <ID>17987</ID>
    <Fecha>2013-10-03T11:45:58</Fecha>
    <Tipo Codigo="3">GENERAL Y PARTICULAR</Tipo>
    <Resultado Codigo="1">APROBADO</Resultado>
    <Quorum Codigo="1">QUORUM SIMPLE</Quorum>
    <Sesion>
      <ID>3002</ID>
      <Numero>78</Numero>
      <Fecha>2013-10-03T10:10:00</Fecha>
      <FechaTermino>0001-01-01T00:00:00</FechaTermino>
      <Tipo Codigo="60">Ordinaria</Tipo>
    </Sesion>
    <Boletin>8843-10</Boletin>
    <Articulo />
    <Tramite Codigo="2">SEGUNDO TRÁMITE</Tramite>
    <Informe Codigo="1">PRIMER INFORME</Informe>
    <TotalAfirmativos>46</TotalAfirmativos>
    <TotalNegativos>0</TotalNegativos>
    <TotalAbstenciones>0</TotalAbstenciones>
    <TotalDispensados>0</TotalDispensados>
  </Votacion>
</Votaciones>