<proyectos><proyecto>
                 <descripcion>
                    <boletin>2931-11</boletin>
                    <titulo>Otorga beneficios a la Salud Primaria</titulo>
                    <fecha_ingreso>14/05/2002</fecha_ingreso>
                    <iniciativa>Mensaje</iniciativa>
                    <camara_origen>C.Diputados</camara_origen>
                    <urgencia_actual>Sin urgencia</urgencia_actual>
                    <etapa>Tramitación terminada</etapa>
                    <subetapa> /  </subetapa>
                    <leynro>Ley Nº 19.813</leynro>
                    <diariooficial>25/06/2002</diariooficial>
                    <estado>Publicado </estado>
                    <refundidos></refundidos>
                    <link_mensaje_mocion>http://www.senado.cl/appsenado/index.php?mo=tramitacion&amp;ac=getDocto&amp;iddocto=3217&amp;tipodoc=mensaje_mocion</link_mensaje_mocion>
                 </descripcion><autores></autores>
<tramitacion><tramite><SESION>/</SESION><FECHA>14/05/2002</FECHA><DESCRIPCIONTRAMITE>Ingreso de proyecto .  </DESCRIPCIONTRAMITE><ETAPDESCRIPCION>Primer trámite constitucional</ETAPDESCRIPCION><CAMARATRAMITE>C.Diputados</CAMARATRAMITE></tramite>
<tramite><SESION>21/346</SESION><FECHA>14/05/2002</FECHA><DESCRIPCIONTRAMITE>Cuenta de proyecto . Pasa a Comisión de Salud</DESCRIPCIONTRAMITE><ETAPDESCRIPCION>Primer trámite constitucional</ETAPDESCRIPCION><CAMARATRAMITE>C.Diputados</CAMARATRAMITE></tramite>
<tramite><SESION>/</SESION><FECHA>14/05/2002</FECHA><DESCRIPCIONTRAMITE>Primer informe de comisión de Salud.  </DESCRIPCIONTRAMITE><ETAPDESCRIPCION>Primer trámite constitucional</ETAPDESCRIPCION><CAMARATRAMITE>C.Diputados</CAMARATRAMITE></tramite>
<tramite><SESION>22/346</SESION><FECHA>15/05/2002</FECHA><DESCRIPCIONTRAMITE>Cuenta de primer informe de comisión .  </DESCRIPCIONTRAMITE><ETAPDESCRIPCION>Primer trámite constitucional</ETAPDESCRIPCION><CAMARATRAMITE>C.Diputados</CAMARATRAMITE></tramite>
<tramite><SESION>22/346</SESION><FECHA>15/05/2002</FECHA><DESCRIPCIONTRAMITE>Discusión general . Aprobado en general y particular a la vez </DESCRIPCIONTRAMITE><ETAPDESCRIPCION>Primer trámite constitucional</ETAPDESCRIPCION><CAMARATRAMITE>C.Diputados</CAMARATRAMITE></tramite>
<tramite><SESION>/</SESION><FECHA>15/05/2002</FECHA><DESCRIPCIONTRAMITE>Oficio de ley a Cámara Revisora .  </DESCRIPCIONTRAMITE><ETAPDESCRIPCION>Primer trámite constitucional</ETAPDESCRIPCION><CAMARATRAMITE>C.Diputados</CAMARATRAMITE></tramite>
<tramite><SESION>16/346</SESION><FECHA>15/05/2002</FECHA><DESCRIPCIONTRAMITE>Pasa a Comisión Hacienda y Salud</DESCRIPCIONTRAMITE><ETAPDESCRIPCION>Segundo trámite constitucional</ETAPDESCRIPCION><CAMARATRAMITE>Senado</CAMARATRAMITE></tramite>
<tramite><SESION>/</SESION><FECHA>12/06/2002</FECHA><DESCRIPCIONTRAMITE>Primer informe de comisión de Hacienda y de Salud, unidas.  </DESCRIPCIONTRAMITE><ETAPDESCRIPCION>Segundo trámite constitucional</ETAPDESCRIPCION><CAMARATRAMITE>Senado</CAMARATRAMITE></tramite>
<tramite><SESION>6/347</SESION><FECHA>12/06/2002</FECHA><DESCRIPCIONTRAMITE>Cuenta verbal informes Comisiones de Salud y Hacienda</DESCRIPCIONTRAMITE><ETAPDESCRIPCION>Segundo trámite constitucional</ETAPDESCRIPCION><CAMARATRAMITE>Senado</CAMARATRAMITE></tramite>
<tramite><SESION>6/347</SESION><FECHA>12/06/2002</FECHA><DESCRIPCIONTRAMITE>Discusión general . Aprobado en general y particular con modificaciones </DESCRIPCIONTRAMITE><ETAPDESCRIPCION>Segundo trámite constitucional</ETAPDESCRIPCION><CAMARATRAMITE>Senado</CAMARATRAMITE></tramite>
<tramite><SESION>/</SESION><FECHA>12/06/2002</FECHA><DESCRIPCIONTRAMITE>Oficio modificaciones a Cámara de Origen .  </DESCRIPCIONTRAMITE><ETAPDESCRIPCION>Segundo trámite constitucional</ETAPDESCRIPCION><CAMARATRAMITE>Senado</CAMARATRAMITE></tramite>
<tramite><SESION>7/347</SESION><FECHA>13/06/2002</FECHA><DESCRIPCIONTRAMITE>Cuenta oficio con modificaciones de Cámara Revisora . Queda para tabla </DESCRIPCIONTRAMITE><ETAPDESCRIPCION>Tercer trámite constitucional</ETAPDESCRIPCION><CAMARATRAMITE>C.Diputados</CAMARATRAMITE></tramite>
<tramite><SESION>7/347</SESION><FECHA>13/06/2002</FECHA><DESCRIPCIONTRAMITE>Discusión única . Aprobadas las modificaciones </DESCRIPCIONTRAMITE><ETAPDESCRIPCION>Tercer trámite constitucional</ETAPDESCRIPCION><CAMARATRAMITE>C.Diputados</CAMARATRAMITE></tramite>
<tramite><SESION>/</SESION><FECHA>13/06/2002</FECHA><DESCRIPCIONTRAMITE>Oficio de ley al Ejecutivo .  </DESCRIPCIONTRAMITE><ETAPDESCRIPCION>Tercer trámite constitucional</ETAPDESCRIPCION><CAMARATRAMITE>C.Diputados</CAMARATRAMITE></tramite>
<tramite><SESION>/</SESION><FECHA>13/06/2002</FECHA><DESCRIPCIONTRAMITE>Oficio Nº 3801, que comunica aprobación de modificaciones</DESCRIPCIONTRAMITE><ETAPDESCRIPCION>Tercer trámite constitucional</ETAPDESCRIPCION><CAMARATRAMITE>C.Diputados</CAMARATRAMITE></tramite>
<tramite><SESION>7/347</SESION><FECHA>18/06/2002</FECHA><DESCRIPCIONTRAMITE>Cuenta oficio Nº 3801, que comunica aprobación de modificaciones</DESCRIPCIONTRAMITE><ETAPDESCRIPCION>Tercer trámite constitucional</ETAPDESCRIPCION><CAMARATRAMITE>Senado</CAMARATRAMITE></tramite>
<tramite><SESION>7/347</SESION><FECHA>18/06/2002</FECHA><DESCRIPCIONTRAMITE>Cuenta, en el Senado, del oficio de la Cámara de Diputados, en el que se comunica que ésta ha aprobado las modificaciones introducidas por el Senado.</DESCRIPCIONTRAMITE><ETAPDESCRIPCION>Tercer trámite constitucional</ETAPDESCRIPCION><CAMARATRAMITE>C.Diputados</CAMARATRAMITE></tramite>
</tramitacion>
<votaciones></votaciones>
<urgencias><urgencia><TIPO>Discusión inmediata</TIPO><FECHAINGRESO>14/05/2002</FECHAINGRESO><MENSAJEINGRESO>120-346</MENSAJEINGRESO><FECHARETIRO>28/05/2002</FECHARETIRO><MENSAJERETIRO>4</MENSAJERETIRO></urgencia>
<urgencia><TIPO>Discusión inmediata</TIPO><FECHAINGRESO>14/05/2002</FECHAINGRESO><MENSAJEINGRESO>115-346</MENSAJEINGRESO><FECHARETIRO>13/06/2002</FECHARETIRO><MENSAJERETIRO>CADUCADA</MENSAJERETIRO></urgencia>
<urgencia><TIPO>Discusión inmediata</TIPO><FECHAINGRESO>28/05/2002</FECHAINGRESO><MENSAJEINGRESO>4</MENSAJEINGRESO><FECHARETIRO>28/05/2002</FECHARETIRO><MENSAJERETIRO>5</MENSAJERETIRO></urgencia>
<urgencia><TIPO>Discusión inmediata</TIPO><FECHAINGRESO>04/06/2002</FECHAINGRESO><MENSAJEINGRESO>36-347</MENSAJEINGRESO><FECHARETIRO>11/06/2002</FECHARETIRO><MENSAJERETIRO>46-347</MENSAJERETIRO></urgencia>
<urgencia><TIPO>Discusión inmediata</TIPO><FECHAINGRESO>11/06/2002</FECHAINGRESO><MENSAJEINGRESO>46-347</MENSAJEINGRESO><FECHARETIRO>11/07/2002</FECHARETIRO><MENSAJERETIRO>CADUCADA</MENSAJERETIRO></urgencia>
</urgencias>
<informes><informe><FECHAINFORME>14/05/2002</FECHAINFORME><TRAMITE>Primer informe de comisión de Salud </TRAMITE><ETAPA>Primer trámite constitucional</ETAPA><LINK_INFORME>http://www.senado.cl/appsenado/index.php?mo=tramitacion&amp;ac=getDocto&amp;iddocto=4390&amp;tipodoc=info</LINK_INFORME></informe>
<informe><FECHAINFORME>12/06/2002</FECHAINFORME><TRAMITE>Primer informe de comisión de Hacienda y de Salud, unidas </TRAMITE><ETAPA>Segundo trámite constitucional</ETAPA><LINK_INFORME>http://www.senado.cl/appsenado/index.php?mo=tramitacion&amp;ac=getDocto&amp;iddocto=4416&amp;tipodoc=info</LINK_INFORME></informe>
</informes>
<comparados></comparados>
<oficios><oficio><NUMERO>3752</NUMERO><FECHA>15/05/2002</FECHA><TRAMITE>Oficio de ley a Cámara Revisora</TRAMITE><ETAPA>Primer trámite constitucional</ETAPA><TIPO>Ley</TIPO><CAMARA>C. Diputados</CAMARA><LINK_OFICIO>http://www.senado.cl/appsenado/index.php?mo=tramitacion&amp;ac=getDocto&amp;iddocto=4666&amp;tipodoc=ofic</LINK_OFICIO></oficio>
<oficio><NUMERO>20009</NUMERO><FECHA>12/06/2002</FECHA><TRAMITE>Oficio modificaciones a Cámara de Origen</TRAMITE><ETAPA>Segundo trámite constitucional</ETAPA><TIPO>Ley</TIPO><CAMARA>Senado</CAMARA><LINK_OFICIO>http://www.senado.cl/appsenado/index.php?mo=tramitacion&amp;ac=getDocto&amp;iddocto=4700&amp;tipodoc=ofic</LINK_OFICIO></oficio>
<oficio><NUMERO>3793</NUMERO><FECHA>13/06/2002</FECHA><TRAMITE>Oficio de ley al Ejecutivo</TRAMITE><ETAPA>Tercer trámite constitucional</ETAPA><TIPO>Ley</TIPO><CAMARA>C. Diputados</CAMARA><LINK_OFICIO>http://www.senado.cl/appsenado/index.php?mo=tramitacion&amp;ac=getDocto&amp;iddocto=4752&amp;tipodoc=ofic</LINK_OFICIO></oficio>
<oficio><NUMERO>3801</NUMERO><FECHA>13/06/2002</FECHA><TRAMITE>Oficio aprobación de modificaciones a Cámara Revisora</TRAMITE><ETAPA>Tercer trámite constitucional</ETAPA><TIPO>Aprobación de modificaciones</TIPO><CAMARA>C. Diputados</CAMARA><LINK_OFICIO>http://www.senado.cl/appsenado/index.php?mo=tramitacion&amp;ac=getDocto&amp;iddocto=9144&amp;tipodoc=ofic</LINK_OFICIO></oficio>
</oficios>
<indicaciones></indicaciones>
<observaciones></observaciones>
<materias><materia><DESCRIPCION>ATENCION PRIMARIA DE LA SALUD </DESCRIPCION></materia>
</materias>
</proyecto>
</proyectos>
