<proyectos><proyecto>
                 <descripcion>
                    <boletin>11856-24</boletin>
                    <titulo>Autoriza erigir un monumento en memoria del nadador Víctor Guillermo Contreras Olguín</titulo>
                    <fecha_ingreso>27/06/2018</fecha_ingreso>
                    <iniciativa>Moción</iniciativa>
                    <camara_origen>C.Diputados</camara_origen>
                    <urgencia_actual>Sin urgencia</urgencia_actual>
                    <etapa>Segundo trámite constitucional (Senado)</etapa>
                    <subetapa>Primer informe de comisión de Educación y Cultura</subetapa>
                    <leynro></leynro>
                    <diariooficial></diariooficial>
                    <estado>En tramitación </estado>
                    <refundidos></refundidos>
                    <link_mensaje_mocion>http://www.senado.cl/appsenado/index.php?mo=tramitacion&amp;ac=getDocto&amp;iddocto=12377&amp;tipodoc=mensaje_mocion</link_mensaje_mocion>
                 </descripcion><autores><autor><PARLAMENTARIO>Fuenzalida Cobo, Juan</PARLAMENTARIO></autor>
<autor><PARLAMENTARIO>Hernández Hernández, Javier</PARLAMENTARIO></autor>
<autor><PARLAMENTARIO>Hoffmann Opazo, María José</PARLAMENTARIO></autor>
<autor><PARLAMENTARIO>Morales Muñoz, Celso</PARLAMENTARIO></autor>
<autor><PARLAMENTARIO>Noman Garrido, Nicolás</PARLAMENTARIO></autor>
<autor><PARLAMENTARIO>Rentería Moller, Rolando</PARLAMENTARIO></autor>
<autor><PARLAMENTARIO>Urrutia Soto, Osvaldo</PARLAMENTARIO></autor>
<autor><PARLAMENTARIO>Von Mühlenbrock Zamora, Gastón</PARLAMENTARIO></autor>
</autores>
<tramitacion><tramite><SESION>/</SESION><FECHA>27/06/2018</FECHA><DESCRIPCIONTRAMITE>Ingreso de proyecto .  </DESCRIPCIONTRAMITE><ETAPDESCRIPCION>Primer trámite constitucional</ETAPDESCRIPCION><CAMARATRAMITE>C.Diputados</CAMARATRAMITE></tramite>
<tramite><SESION>41/366</SESION><FECHA>03/07/2018</FECHA><DESCRIPCIONTRAMITE>Cuenta de proyecto . Pasa a Comisión de la Cultura y las Artes</DESCRIPCIONTRAMITE><ETAPDESCRIPCION>Primer trámite constitucional</ETAPDESCRIPCION><CAMARATRAMITE>C.Diputados</CAMARATRAMITE></tramite>
<tramite><SESION>/</SESION><FECHA>13/10/2018</FECHA><DESCRIPCIONTRAMITE>Primer informe de comisión de Cultura, Artes y Comunicaciones.  </DESCRIPCIONTRAMITE><ETAPDESCRIPCION>Primer trámite constitucional</ETAPDESCRIPCION><CAMARATRAMITE>C.Diputados</CAMARATRAMITE></tramite>
<tramite><SESION>85/366</SESION><FECHA>16/10/2018</FECHA><DESCRIPCIONTRAMITE>Cuenta de primer informe de comisión .  </DESCRIPCIONTRAMITE><ETAPDESCRIPCION>Primer trámite constitucional</ETAPDESCRIPCION><CAMARATRAMITE>C.Diputados</CAMARATRAMITE></tramite>
<tramite><SESION>85/366</SESION><FECHA>16/10/2018</FECHA><DESCRIPCIONTRAMITE>Discusión general . Aprobado en general y particular a la vez .</DESCRIPCIONTRAMITE><ETAPDESCRIPCION>Primer trámite constitucional</ETAPDESCRIPCION><CAMARATRAMITE>C.Diputados</CAMARATRAMITE></tramite>
<tramite><SESION>/</SESION><FECHA>16/10/2018</FECHA><DESCRIPCIONTRAMITE>Oficio de ley a Cámara Revisora .   N° 14.290, a segundo trámite constitucional.</DESCRIPCIONTRAMITE><ETAPDESCRIPCION>Primer trámite constitucional</ETAPDESCRIPCION><CAMARATRAMITE>C.Diputados</CAMARATRAMITE></tramite>
<tramite><SESION>60/366</SESION><FECHA>16/10/2018</FECHA><DESCRIPCIONTRAMITE>Cuenta de proyecto . Pasa a Comisión de Educación y Cultura</DESCRIPCIONTRAMITE><ETAPDESCRIPCION>Segundo trámite constitucional</ETAPDESCRIPCION><CAMARATRAMITE>Senado</CAMARATRAMITE></tramite>
</tramitacion>
<votaciones></votaciones>
<urgencias></urgencias>
<informes><informe><FECHAINFORME>16/10/2018</FECHAINFORME><TRAMITE>Primer informe de comisión de Cultura, Artes y Comunicaciones </TRAMITE><ETAPA>Primer trámite constitucional</ETAPA><LINK_INFORME>http://www.senado.cl/appsenado/index.php?mo=tramitacion&amp;ac=getDocto&amp;iddocto=20770&amp;tipodoc=info</LINK_INFORME></informe>
</informes>
<comparados></comparados>
<oficios><oficio><NUMERO>14.290</NUMERO><FECHA>16/10/2018</FECHA><TRAMITE>Oficio de ley a Cámara Revisora</TRAMITE><ETAPA>Primer trámite constitucional</ETAPA><TIPO>Ley</TIPO><CAMARA>C. Diputados</CAMARA><LINK_OFICIO>http://www.senado.cl/appsenado/index.php?mo=tramitacion&amp;ac=getDocto&amp;iddocto=24016&amp;tipodoc=ofic</LINK_OFICIO></oficio>
</oficios>
<indicaciones></indicaciones>
<observaciones></observaciones>
<materias><materia><DESCRIPCION>MONUMENTOS NACIONALES</DESCRIPCION></materia>
<materia><DESCRIPCION>VICTOR GUILLERMO CONTRERAS OLGUIN</DESCRIPCION></materia>
</materias>
</proyecto>
</proyectos>
