{"TotalAbstenciones": "8", "Resultado": "APROBADO", "Quorum": "REFORMA CONSTITUCIONAL 2/3", "Tipo": "GENERAL", "Informe": "PRIMER INFORME", "Fecha": "2018-01-10T13:45:17", "TotalAfirmativos": "97", "TotalNegativos": "9", "Temas": [["Trabajo_y_prevision_social", ["constitucional(232)", "proyecto(121)", "regulacion(11)", "constitucion(344)", "constitucionales(36)", "institucionalidad(13)", "nacional(49)", "administracion(17)", "procedimiento(16)", "administrativo(8)", "consejo(6)", "nacionalidad(16)", "indemnizacion(8)", "causales(12)", "redaccion(7)", "facultades(30)", "comisiones(6)", "especiales(6)", "empresas(6)", "destitucion(8)", "facultad(6)", "dias(11)", "proyectos(48)", "tramitacion(15)", "normas(26)", "situacion(8)", "regionales(22)", "norma(10)", "trabajo(18)", "apelaciones(8)", "control(24)", "calificacion(10)", "preventivo(14)", "procedimientos(6)", "contar(6)", "fondo(12)", "consenso(6)", "institucion(12)", "relacion(28)", "presentacion(8)", "institucional(32)", "servicio(6)", "expresion(6)", "producto(8)", "indicacion(10)"]], ["Justicia_y_derechos_humanos", ["legislacion(34)", "justicia(38)", "diputado(62)", "derechos(34)", "nacional(49)", "judicial(17)", "tribunal(108)", "diputados(67)", "sentencias(6)", "derecho(132)", "procedimiento(16)", "ciudadania(28)", "articulo(53)", "nacionalidad(16)", "gracia(14)", "pena(30)", "penal(10)", "fiscales(18)", "fiscalia(6)", "judiciales(16)", "ejecutivo(36)", "procedimientos(6)", "integrantes(8)", "derecha(16)", "legislativo(10)", "ciudadano(6)", "ciudadanos(6)", "ciudadana(8)"]], ["Medio_ambiente_y_bienes_nacionales", ["comision(76)", "constitucionales(36)", "derechos(34)", "nacional(98)", "derecho(132)", "nacionalidad(16)", "ambito(12)", "tambien(50)", "comisiones(6)", "ano(8)", "funcion(8)", "alguna(8)", "apelaciones(8)", "funciones(28)", "isla(24)", "varios(9)", "camino(24)", "cosas(8)", "lagos(12)", "nivel(12)", "politicos(6)", "medios(6)", "cambio(36)", "cambios(20)", "decision(8)", "cambiando(8)"]]], "Articulo": "números 9 a 21, 23 y 24 del artículo único del proyecto de reforma constitucional.", "Boletin": "11342-07", "Sesion": {"Fecha": "2018-01-10T10:36:40", "Tipo": "Ordinaria", "ID": "3574", "Numero": "111", "FechaTermino": "0001-01-01T00:00:00"}, "Tramite": "PRIMER TRÁMITE", "ID": "26901", "TotalDispensados": "0"}