{"proyectos": {"proyecto": {"descripcion": {"boletin": "7730-12", "titulo": "Modifica ley N° 19.300, sobre Bases Generales del Medio Ambiente, que  obliga a someter los proyectos de exploración y explotación de energía geotérmica, al sistema de evaluación de impacto ambiental.", "fecha_ingreso": "16/06/2011", "iniciativa": "Moción", "camara_origen": "C.Diputados", "urgencia_actual": "Sin urgencia", "etapa": "Primer trámite constitucional (C.Diputados)", "subetapa": "Primer informe de comisión Medio Ambiente y Recursos Naturales", "leynro": null, "diariooficial": null, "estado": "En tramitación", "refundidos": null, "link_mensaje_mocion": "http://www.senado.cl/appsenado/index.php?mo=tramitacion&ac=getDocto&iddocto=8126&tipodoc=mensaje_mocion"}, "autores": {"autor": [{"PARLAMENTARIO": "Burgos Varela, Jorge"}, {"PARLAMENTARIO": "Cerda García, Eduardo"}, {"PARLAMENTARIO": "Chahin Valenzuela, Fuad"}, {"PARLAMENTARIO": "Espinosa Monardes, Marcos"}, {"PARLAMENTARIO": "Girardi Lavín, Cristina"}, {"PARLAMENTARIO": "Goic Boroevic, Carolina"}, {"PARLAMENTARIO": "Isasi Barbieri, Marta"}, {"PARLAMENTARIO": "Saffirio Espinoza, René"}, {"PARLAMENTARIO": "Torres Jeldes, Víctor"}, {"PARLAMENTARIO": "Vallespín López, Patricio"}]}, "tramitacion": {"tramite": [{"SESION": "/", "FECHA": "16/06/2011", "DESCRIPCIONTRAMITE": "Ingreso de proyecto .", "ETAPDESCRIPCION": "Primer trámite constitucional", "CAMARATRAMITE": "C.Diputados"}, {"SESION": "44/359", "FECHA": "16/06/2011", "DESCRIPCIONTRAMITE": "Cuenta de proyecto . Pasa a Comisión de Recursos Naturales, Bienes Nacionales y Medio Ambiente", "ETAPDESCRIPCION": "Primer trámite constitucional", "CAMARATRAMITE": "C.Diputados"}]}, "votaciones": null, "urgencias": null, "informes": null, "comparados": null, "oficios": null, "indicaciones": null, "observaciones": null, "materias": {"materia": [{"DESCRIPCION": "ANÁLISIS DEL IMPACTO AMBIENTAL"}, {"DESCRIPCION": "BASES GENERALES DEL MEDIO AMBIENTE"}, {"DESCRIPCION": "ENERGIA GEOTERMICA"}, {"DESCRIPCION": "MEDIO AMBIENTE"}, {"DESCRIPCION": "SISTEMA DE EVALUACIÓN DE IMPACTO AMBIENTAL"}]}}}, "ID": "7730"}