{"proyectos": {"proyecto": {"descripcion": {"boletin": "3577-03", "titulo": "Interpreta el artículo 26 del decreto ley Nº 3.063, de 1979, con el propósito de facilitar el funcionamiento de microempresas familiares.", "fecha_ingreso": "22/06/2004", "iniciativa": "Moción", "camara_origen": "Senado", "urgencia_actual": "Sin urgencia", "etapa": "Tramitación terminada", "subetapa": "/", "leynro": "Ley Nº 20.031", "diariooficial": "08/07/2005", "estado": "Publicado", "refundidos": null, "link_mensaje_mocion": "http://www.senado.cl/appsenado/index.php?mo=tramitacion&ac=getDocto&iddocto=3901&tipodoc=mensaje_mocion"}, "autores": {"autor": [{"PARLAMENTARIO": "Sabag Castillo, Hosaín"}, {"PARLAMENTARIO": "Zaldívar Larraín, Andrés"}]}, "tramitacion": {"tramite": [{"SESION": "/", "FECHA": "22/06/2004", "DESCRIPCIONTRAMITE": "Ingreso de proyecto .", "ETAPDESCRIPCION": "Primer trámite constitucional", "CAMARATRAMITE": "C.Diputados"}, {"SESION": "6/351", "FECHA": "22/06/2004", "DESCRIPCIONTRAMITE": "Cuenta de proyecto . Pasa a Comisión de Economía", "ETAPDESCRIPCION": "Primer trámite constitucional", "CAMARATRAMITE": "C.Diputados"}, {"SESION": "/", "FECHA": "02/08/2004", "DESCRIPCIONTRAMITE": "Primer informe de comisión de Economía.", "ETAPDESCRIPCION": "Primer trámite constitucional", "CAMARATRAMITE": "C.Diputados"}, {"SESION": "16/351", "FECHA": "03/08/2004", "DESCRIPCIONTRAMITE": "Cuenta de primer informe de comisión .", "ETAPDESCRIPCION": "Primer trámite constitucional", "CAMARATRAMITE": "C.Diputados"}, {"SESION": "26/351", "FECHA": "07/09/2004", "DESCRIPCIONTRAMITE": "Discusión general . Aprobado en general y particular a la vez", "ETAPDESCRIPCION": "Primer trámite constitucional", "CAMARATRAMITE": "C.Diputados"}, {"SESION": "/", "FECHA": "08/09/2004", "DESCRIPCIONTRAMITE": "Oficio de ley a Cámara Revisora .", "ETAPDESCRIPCION": "Primer trámite constitucional", "CAMARATRAMITE": "C.Diputados"}, {"SESION": "40/351", "FECHA": "08/09/2004", "DESCRIPCIONTRAMITE": "Cuenta de proyecto . Pasa a Comisión Especial PYMES", "ETAPDESCRIPCION": "Segundo trámite constitucional", "CAMARATRAMITE": "Senado"}, {"SESION": "/", "FECHA": "08/09/2004", "DESCRIPCIONTRAMITE": "Primer informe de comisión de Micro, Pequeña y Mediana Empresa.", "ETAPDESCRIPCION": "Segundo trámite constitucional", "CAMARATRAMITE": "Senado"}, {"SESION": "2/352", "FECHA": "05/10/2004", "DESCRIPCIONTRAMITE": "Cuenta del Mensaje 35-352 que hace presente la urgencia Discusión inmediata", "ETAPDESCRIPCION": "Segundo trámite constitucional", "CAMARATRAMITE": "Senado"}, {"SESION": "/", "FECHA": "05/10/2004", "DESCRIPCIONTRAMITE": "Primer informe de comisión de Hacienda.", "ETAPDESCRIPCION": "Segundo trámite constitucional", "CAMARATRAMITE": "Senado"}, {"SESION": "2/352", "FECHA": "06/10/2004", "DESCRIPCIONTRAMITE": "Cuenta de primer informe de comisión .", "ETAPDESCRIPCION": "Segundo trámite constitucional", "CAMARATRAMITE": "Senado"}, {"SESION": "2/352", "FECHA": "06/10/2004", "DESCRIPCIONTRAMITE": "Discusión general . Aprobado en general", "ETAPDESCRIPCION": "Segundo trámite constitucional", "CAMARATRAMITE": "Senado"}, {"SESION": "/", "FECHA": "08/10/2004", "DESCRIPCIONTRAMITE": "Segundo informe de comisión de Micro, Pequeña y Mediana Empresa.", "ETAPDESCRIPCION": "Segundo trámite constitucional", "CAMARATRAMITE": "Senado"}, {"SESION": "4/352", "FECHA": "12/10/2004", "DESCRIPCIONTRAMITE": "Cuenta de segundo informe de comisión .", "ETAPDESCRIPCION": "Segundo trámite constitucional", "CAMARATRAMITE": "Senado"}, {"SESION": "5/352", "FECHA": "12/10/2004", "DESCRIPCIONTRAMITE": "Discusión particular . Aprobado con modificaciones", "ETAPDESCRIPCION": "Segundo trámite constitucional", "CAMARATRAMITE": "Senado"}, {"SESION": "/", "FECHA": "12/10/2004", "DESCRIPCIONTRAMITE": "Oficio modificaciones a Cámara de Origen .", "ETAPDESCRIPCION": "Segundo trámite constitucional", "CAMARATRAMITE": "Senado"}, {"SESION": "5/352", "FECHA": "13/10/2004", "DESCRIPCIONTRAMITE": "Cuenta oficio con modificaciones de Cámara Revisora . Queda para tabla", "ETAPDESCRIPCION": "Tercer trámite constitucional", "CAMARATRAMITE": "C.Diputados"}, {"SESION": "11/352", "FECHA": "09/11/2004", "DESCRIPCIONTRAMITE": "Discusión única . Rechazadas las modificaciones", "ETAPDESCRIPCION": "Tercer trámite constitucional", "CAMARATRAMITE": "C.Diputados"}, {"SESION": "/", "FECHA": "10/11/2004", "DESCRIPCIONTRAMITE": "Oficio rechazo modificaciones a Cámara Revisora .", "ETAPDESCRIPCION": "Tercer trámite constitucional", "CAMARATRAMITE": "C.Diputados"}, {"SESION": "18/352", "FECHA": "11/11/2004", "DESCRIPCIONTRAMITE": "Cuenta oficio rechazo a modificaciones .  Cuenta en Cámara de Diputados de oficio rechazo a modificaciones", "ETAPDESCRIPCION": "Comisión Mixta por rechazo de modificaciones", "CAMARATRAMITE": "Senado"}, {"SESION": "/", "FECHA": "11/11/2004", "DESCRIPCIONTRAMITE": "Oficio integrantes de Comisión Mixta .  al Senado", "ETAPDESCRIPCION": "Comisión Mixta por rechazo de modificaciones", "CAMARATRAMITE": "C.Diputados"}, {"SESION": "13/352", "FECHA": "16/11/2004", "DESCRIPCIONTRAMITE": "Cuenta oficio integrantes de Comisión Mixta .", "ETAPDESCRIPCION": "Comisión Mixta por rechazo de modificaciones", "CAMARATRAMITE": "Senado"}, {"SESION": "/", "FECHA": "18/05/2005", "DESCRIPCIONTRAMITE": "Informe de Comisión Mixta Comisión Mixta para Boletín Nº 3577-03. Microempresas familiares..", "ETAPDESCRIPCION": "Comisión Mixta por rechazo de modificaciones", "CAMARATRAMITE": "Senado"}, {"SESION": "54/352", "FECHA": "18/05/2005", "DESCRIPCIONTRAMITE": "Cuenta informe Comisión Mixta .", "ETAPDESCRIPCION": "Disc. informe C.Mixta por rechazo de modific. en C. Origen", "CAMARATRAMITE": "C.Diputados"}, {"SESION": "1/353", "FECHA": "07/06/2005", "DESCRIPCIONTRAMITE": "Discusión informe de Comisión Mixta . Aprobado", "ETAPDESCRIPCION": "Disc. informe C.Mixta por rechazo de modific. en C. Origen", "CAMARATRAMITE": "C.Diputados"}, {"SESION": "/", "FECHA": "08/06/2005", "DESCRIPCIONTRAMITE": "Oficio aprobación de informe de Comisión Mixta a C. Revisora .", "ETAPDESCRIPCION": "Disc. informe C.Mixta por rechazo de modific. en C. Origen", "CAMARATRAMITE": "C.Diputados"}, {"SESION": "4/353", "FECHA": "08/06/2005", "DESCRIPCIONTRAMITE": "Cuenta oficio aprobación de informe de Comisión Mixta .", "ETAPDESCRIPCION": "Disc. informe C.Mixta por rechazo de modif. C. Revisora", "CAMARATRAMITE": "Senado"}, {"SESION": "4/353", "FECHA": "08/06/2005", "DESCRIPCIONTRAMITE": "Discusión informe de Comisión Mixta . Aprobado", "ETAPDESCRIPCION": "Disc. informe C.Mixta por rechazo de modif. C. Revisora", "CAMARATRAMITE": "Senado"}, {"SESION": "/", "FECHA": "08/06/2005", "DESCRIPCIONTRAMITE": "Oficio aprobación de informe de Comisión Mixta a C.de Origen .", "ETAPDESCRIPCION": "Disc. informe C.Mixta por rechazo de modif. C. Revisora", "CAMARATRAMITE": "Senado"}, {"SESION": "6/353", "FECHA": "15/06/2005", "DESCRIPCIONTRAMITE": "Cuenta oficio aprobación de informe de Comisión Mixta .", "ETAPDESCRIPCION": "Trámite finalización en Cámara de Origen", "CAMARATRAMITE": "C.Diputados"}, {"SESION": "/", "FECHA": "16/06/2005", "DESCRIPCIONTRAMITE": "Oficio de ley al Ejecutivo .", "ETAPDESCRIPCION": "Trámite finalización en Cámara de Origen", "CAMARATRAMITE": "C.Diputados"}]}, "votaciones": {"votacion": [{"SESION": "26/351", "FECHA": "07/09/2004", "TEMA": "Aprobación general", "SI": "33", "NO": "0", "ABSTENCION": "0", "TIPOVOTACION": "Discusión general", "ETAPA": "Primer trámite constitucional", "DETALLE_VOTACION": {"VOTO": [{"PARLAMENTARIO": "Flores L., Fernando", "SELECCION": "Si"}, {"PARLAMENTARIO": "Foxley R., Alejandro", "SELECCION": "Si"}, {"PARLAMENTARIO": "Moreno R., Rafael", "SELECCION": "Si"}, {"PARLAMENTARIO": "Frei R., Carmen", "SELECCION": "Si"}, {"PARLAMENTARIO": "Fernández F., Sergio", "SELECCION": "Si"}, {"PARLAMENTARIO": "Novoa V., Jovino"}, {"PARLAMENTARIO": "Gazmuri M., Jaime", "SELECCION": "Si"}, {"PARLAMENTARIO": "Naranjo O., Jaime", "SELECCION": "Si"}, {"PARLAMENTARIO": "Sabag C., Hosaín", "SELECCION": "Si"}, {"PARLAMENTARIO": "Ruiz-Esquide J., Mariano", "SELECCION": "Si"}, {"PARLAMENTARIO": "Frei R., Eduardo", "SELECCION": "Si"}, {"PARLAMENTARIO": "Stange O., Rodolfo", "SELECCION": "Si"}, {"PARLAMENTARIO": "Ávila C., Nelson", "SELECCION": "Si"}, {"PARLAMENTARIO": "Parra M., Augusto", "SELECCION": "Si"}, {"PARLAMENTARIO": "Silva C., Enrique", "SELECCION": "Si"}, {"PARLAMENTARIO": "Martínez B., Jorge", "SELECCION": "Si"}, {"PARLAMENTARIO": "Canessa R., Julio", "SELECCION": "Si"}, {"PARLAMENTARIO": "Zurita C., Enrique", "SELECCION": "Si"}, {"PARLAMENTARIO": "Cordero R., Fernando", "SELECCION": "Si"}, {"PARLAMENTARIO": "Boeninger K., Edgardo", "SELECCION": "Si"}, {"PARLAMENTARIO": "Romero P., Sergio", "SELECCION": "Si"}, {"PARLAMENTARIO": "Espina O., Alberto", "SELECCION": "Si"}, {"PARLAMENTARIO": "Orpis B., Jaime", "SELECCION": "Si"}, {"PARLAMENTARIO": "Coloma C., Juan Antonio", "SELECCION": "Si"}, {"PARLAMENTARIO": "Ríos S., Mario", "SELECCION": "Si"}, {"PARLAMENTARIO": "Cantero O., Carlos", "SELECCION": "Si"}, {"PARLAMENTARIO": "Prokurica P., Baldo", "SELECCION": "Si"}, {"PARLAMENTARIO": "Horvath K., Antonio", "SELECCION": "Si"}, {"PARLAMENTARIO": "__", "SELECCION": "Si"}, {"PARLAMENTARIO": "Muñoz B., Roberto", "SELECCION": "Si"}, {"PARLAMENTARIO": "Núñez M., Ricardo", "SELECCION": "Si"}, {"PARLAMENTARIO": "Zaldívar L., Andrés", "SELECCION": "Si"}, {"PARLAMENTARIO": "Chadwick P., Andrés", "SELECCION": "Si"}, {"PARLAMENTARIO": "García R., José", "SELECCION": "Si"}]}}, {"SESION": "11/352", "FECHA": "09/11/2004", "TEMA": "modificaciones propuestas por la Cámara de Diputados", "SI": "1", "NO": "39", "ABSTENCION": "0", "TIPOVOTACION": "Discusión única", "ETAPA": "Tercer trámite constitucional", "DETALLE_VOTACION": {"VOTO": [{"PARLAMENTARIO": "__", "SELECCION": "No"}, {"PARLAMENTARIO": "Muñoz B., Roberto", "SELECCION": "No"}, {"PARLAMENTARIO": "Flores L., Fernando", "SELECCION": "No"}, {"PARLAMENTARIO": "Foxley R., Alejandro", "SELECCION": "No"}, {"PARLAMENTARIO": "Moreno R., Rafael", "SELECCION": "No"}, {"PARLAMENTARIO": "Frei R., Carmen", "SELECCION": "No"}, {"PARLAMENTARIO": "Valdés S., Gabriel", "SELECCION": "No"}, {"PARLAMENTARIO": "Arancibia R., Jorge", "SELECCION": "No"}, {"PARLAMENTARIO": "Núñez M., Ricardo", "SELECCION": "No"}, {"PARLAMENTARIO": "Viera-Gallo Q., José Antonio", "SELECCION": "No"}, {"PARLAMENTARIO": "Ominami P., Carlos", "SELECCION": "No"}, {"PARLAMENTARIO": "Naranjo O., Jaime", "SELECCION": "No"}, {"PARLAMENTARIO": "Ruiz D., José", "SELECCION": "No"}, {"PARLAMENTARIO": "Zaldívar L., Andrés", "SELECCION": "No"}, {"PARLAMENTARIO": "Sabag C., Hosaín", "SELECCION": "No"}, {"PARLAMENTARIO": "Lavandero I., Jorge", "SELECCION": "No"}, {"PARLAMENTARIO": "Bombal O., Carlos", "SELECCION": "No"}, {"PARLAMENTARIO": "Chadwick P., Andrés", "SELECCION": "No"}, {"PARLAMENTARIO": "Matthei F., Evelyn", "SELECCION": "No"}, {"PARLAMENTARIO": "Stange O., Rodolfo", "SELECCION": "No"}, {"PARLAMENTARIO": "Ávila C., Nelson", "SELECCION": "No"}, {"PARLAMENTARIO": "Parra M., Augusto", "SELECCION": "No"}, {"PARLAMENTARIO": "Silva C., Enrique", "SELECCION": "No"}, {"PARLAMENTARIO": "Martínez B., Jorge", "SELECCION": "No"}, {"PARLAMENTARIO": "Canessa R., Julio", "SELECCION": "No"}, {"PARLAMENTARIO": "Vega H., Ramón", "SELECCION": "No"}, {"PARLAMENTARIO": "Zurita C., Enrique", "SELECCION": "Si"}, {"PARLAMENTARIO": "Cordero R., Fernando", "SELECCION": "No"}, {"PARLAMENTARIO": "Aburto O., Marcos", "SELECCION": "No"}, {"PARLAMENTARIO": "Boeninger K., Edgardo", "SELECCION": "No"}, {"PARLAMENTARIO": "Romero P., Sergio", "SELECCION": "No"}, {"PARLAMENTARIO": "Espina O., Alberto", "SELECCION": "No"}, {"PARLAMENTARIO": "García R., José", "SELECCION": "No"}, {"PARLAMENTARIO": "Orpis B., Jaime", "SELECCION": "No"}, {"PARLAMENTARIO": "Coloma C., Juan Antonio", "SELECCION": "No"}, {"PARLAMENTARIO": "Ríos S., Mario", "SELECCION": "No"}, {"PARLAMENTARIO": "Cantero O., Carlos", "SELECCION": "No"}, {"PARLAMENTARIO": "Prokurica P., Baldo", "SELECCION": "No"}, {"PARLAMENTARIO": "Horvath K., Antonio", "SELECCION": "No"}, {"PARLAMENTARIO": "__", "SELECCION": "No"}]}}]}, "urgencias": {"urgencia": {"TIPO": "Discusión inmediata", "FECHAINGRESO": "05/10/2004", "MENSAJEINGRESO": "35-352", "CAMARAINGRESO": "C. Diputados", "FECHARETIRO": "04/11/2004", "MENSAJERETIRO": "CADUCADA"}}, "informes": {"informe": [{"FECHAINFORME": "02/08/2004", "TRAMITE": "Primer informe de comisión de Economía", "ETAPA": "Primer trámite constitucional", "LINK_INFORME": "http://www.senado.cl/appsenado/index.php?mo=tramitacion&ac=getDocto&iddocto=6686&tipodoc=info"}, {"FECHAINFORME": "08/09/2004", "TRAMITE": "Primer informe de comisión de Micro, Pequeña y Mediana Empresa", "ETAPA": "Segundo trámite constitucional", "LINK_INFORME": "http://www.senado.cl/appsenado/index.php?mo=tramitacion&ac=getDocto&iddocto=7197&tipodoc=info"}, {"FECHAINFORME": "05/10/2004", "TRAMITE": "Primer informe de comisión de Hacienda", "ETAPA": "Primer trámite constitucional", "LINK_INFORME": "http://www.senado.cl/appsenado/index.php?mo=tramitacion&ac=getDocto&iddocto=7196&tipodoc=info"}, {"FECHAINFORME": "08/10/2004", "TRAMITE": "Segundo informe de comisión de Micro, Pequeña y Mediana Empresa", "ETAPA": "Segundo trámite constitucional", "LINK_INFORME": "http://www.senado.cl/appsenado/index.php?mo=tramitacion&ac=getDocto&iddocto=7204&tipodoc=info"}, {"FECHAINFORME": "18/05/2005", "TRAMITE": "Informe de Comisión Mixta Comisión Mixta para Boletín Nº 3577-03. Microempresas familiares.", "ETAPA": "Comisión Mixta por rechazo de modificaciones", "LINK_INFORME": "http://www.senado.cl/appsenado/index.php?mo=tramitacion&ac=getDocto&iddocto=8287&tipodoc=info"}]}, "comparados": null, "oficios": {"oficio": [{"NUMERO": "24141", "FECHA": "08/09/2004", "TRAMITE": "Oficio de ley a Cámara Revisora", "ETAPA": "Primer trámite constitucional", "TIPO": "Ley", "CAMARA": "Senado", "LINK_OFICIO": "http://www.senado.cl/appsenado/index.php?mo=tramitacion&ac=getDocto&iddocto=7725&tipodoc=ofic"}, {"NUMERO": "5190", "FECHA": "12/10/2004", "TRAMITE": "Oficio modificaciones a Cámara de Origen", "ETAPA": "Segundo trámite constitucional", "TIPO": "Ley", "CAMARA": "C. Diputados", "LINK_OFICIO": "http://www.senado.cl/appsenado/index.php?mo=tramitacion&ac=getDocto&iddocto=9847&tipodoc=ofic"}, {"NUMERO": "24333", "FECHA": "10/11/2004", "TRAMITE": "Oficio rechazo modificaciones a Cámara Revisora", "ETAPA": "Tercer trámite constitucional", "TIPO": "Ley", "CAMARA": "Senado", "LINK_OFICIO": "http://www.senado.cl/appsenado/index.php?mo=tramitacion&ac=getDocto&iddocto=8179&tipodoc=ofic"}, {"NUMERO": "5258", "FECHA": "11/11/2004", "TRAMITE": "Oficio integrantes de Comisión Mixta", "ETAPA": "Comisión Mixta por rechazo de modificaciones", "TIPO": "Ley", "CAMARA": "C. Diputados", "LINK_OFICIO": "http://www.senado.cl/appsenado/index.php?mo=tramitacion&ac=getDocto&iddocto=8211&tipodoc=ofic"}, {"NUMERO": "5617", "FECHA": "08/06/2005", "TRAMITE": "Oficio aprobación de informe de Comisión Mixta a C.de Origen", "ETAPA": "Disc. Informe C.Mixta por rechazo idea de legislar C. Revis.", "TIPO": "Ley", "CAMARA": "C. Diputados", "LINK_OFICIO": "http://www.senado.cl/appsenado/index.php?mo=tramitacion&ac=getDocto&iddocto=9714&tipodoc=ofic"}, {"NUMERO": "25333", "FECHA": "08/06/2005", "TRAMITE": "Oficio aprobación de informe de Comisión Mixta a C. Revisora", "ETAPA": "Disc. informe C.Mixta por rechazo de modific. en C. Origen", "TIPO": "Ley", "CAMARA": "Senado", "LINK_OFICIO": "http://www.senado.cl/appsenado/index.php?mo=tramitacion&ac=getDocto&iddocto=9671&tipodoc=ofic"}, {"NUMERO": "25388", "FECHA": "16/06/2005", "TRAMITE": "Oficio de ley al Ejecutivo", "ETAPA": "Trámite finalización en Cámara de Origen", "TIPO": "Ley", "CAMARA": "Senado", "LINK_OFICIO": "http://www.senado.cl/appsenado/index.php?mo=tramitacion&ac=getDocto&iddocto=9772&tipodoc=ofic"}]}, "indicaciones": null, "observaciones": null, "materias": {"materia": {"DESCRIPCION": "EMPRESAS"}}}}, "ID": "3577"}