{"TotalAbstenciones": "0", "Resultado": "APROBADO", "Quorum": "QUORUM SIMPLE", "Tipo": "GENERAL", "Informe": "PRIMER INFORME", "Fecha": "2007-08-01T12:57:52", "TotalAfirmativos": "98", "TotalNegativos": "0", "Temas": [["Trabajo_y_prevision_social", ["procedimiento(61)", "constitucional(12)", "dia(12)", "proyecto(220)", "documentos(11)", "normas(32)", "constitucion(12)", "poblaciones(46)", "contar(26)", "urbanizacion(163)", "situacion(74)", "servicios(22)", "previsto(6)", "servicio(44)", "contratos(18)", "actos(8)", "contrato(16)", "obligaciones(10)", "representacion(6)", "administracion(6)", "contratar(6)", "indica(6)", "situaciones(21)", "beneficio(20)", "acciones(10)", "urbanizaciones(6)", "sindico(6)", "regionales(6)", "nacionales(6)", "producido(12)", "social(28)", "costo(8)", "sociales(36)", "beneficios(52)", "oportunidad(10)", "solicitar(18)", "dias(20)", "presentacion(12)", "expresa(6)", "proteccion(8)", "pendientes(12)", "contado(16)", "indicacion(32)", "indicaciones(26)", "relacion(24)", "diferentes(8)", "contrario(8)", "tramitacion(13)", "labor(8)", "nacional(11)", "instituciones(8)", "proyectos(8)", "fondos(7)", "fondo(9)", "gente(34)", "trabajar(8)", "trabajado(8)", "unidades(9)"]], ["Vivienda_y_urbanismo", ["regularizacion(66)", "vivienda(304)", "urbano(28)", "obras(262)", "constitucion(6)", "republica(14)", "urbanismo(60)", "poblaciones(92)", "inmuebles(24)", "dominio(122)", "financiamiento(10)", "regularizar(32)", "edificaciones(8)", "construcciones(66)", "urbanizar(8)", "comunidades(6)", "comunidad(6)", "obligaciones(10)", "aprobacion(12)", "poblacion(20)", "comun(8)", "inmueble(24)", "publica(10)", "verificacion(8)", "dirigentes(8)", "publico(8)", "propiedades(32)", "propiedad(48)", "social(14)", "intervencion(6)", "regularizado(14)", "vecinos(28)", "sociales(18)", "propia(18)", "viviendas(82)", "publicos(14)", "publicacion(20)", "indicaciones(26)", "construccion(20)", "diferentes(8)", "comunas(24)", "comuna(8)", "viviendo(16)", "modificaciones(10)"]], ["Hacienda_y_relaciones_exteriores", ["procedimiento(61)", "cuenta(34)", "acuerdo(26)", "republica(14)", "condiciones(56)", "financiamiento(10)", "establecidas(8)", "reservas(8)", "planificacion(6)", "bienes(28)", "encuentra(8)", "situaciones(21)", "anos(46)", "publica(10)", "tasacion(7)", "acciones(30)", "nacionales(6)", "bien(19)", "intervencion(6)", "bancos(12)", "financieros(12)", "deuda(16)", "tratandose(28)", "indicaciones(26)", "relacion(12)", "trata(9)", "financieras(8)", "cuentan(8)", "duda(20)", "contencion(6)", "puesto(6)", "tratado(6)", "aspiraciones(6)", "economicos(10)"]]], "Articulo": "Con excepción de los incisos tercero, quinto y sexto del artículo 4°.\n", "Boletin": "4981-14", "Sesion": {"Fecha": "2007-08-01T10:38:00", "Tipo": "Ordinaria", "ID": "1932", "Numero": "58", "FechaTermino": "0001-01-01T00:00:00"}, "Tramite": "PRIMER TRÁMITE", "ID": "7001", "TotalDispensados": "0"}