{"proyectos": {"proyecto": {"descripcion": {"boletin": "2275-05", "titulo": "Modifica el artículo 46 de la Ley Nº 18.899, que concede beneficios tributarios a las donaciones a favor de la fundación Teresa de Los Andes.", "fecha_ingreso": "10/12/1998", "iniciativa": "Mensaje", "camara_origen": "C.Diputados", "urgencia_actual": "Sin urgencia", "etapa": "Tramitación terminada", "subetapa": "/", "leynro": "Ley Nº 19.599", "diariooficial": "31/12/1998", "estado": "Publicado", "refundidos": null, "link_mensaje_mocion": "http://www.senado.cl/appsenado/index.php?mo=tramitacion&ac=getDocto&iddocto=2742&tipodoc=mensaje_mocion"}, "autores": null, "tramitacion": {"tramite": [{"SESION": "26/339", "FECHA": "10/12/1998", "DESCRIPCIONTRAMITE": "Cuenta de proyecto . Pasa a Comisión de Hacienda", "ETAPDESCRIPCION": "Primer trámite constitucional", "CAMARATRAMITE": "C.Diputados"}, {"SESION": "/", "FECHA": "10/12/1998", "DESCRIPCIONTRAMITE": "Ingreso de proyecto .", "ETAPDESCRIPCION": "Primer trámite constitucional", "CAMARATRAMITE": "C.Diputados"}, {"SESION": "27/339", "FECHA": "15/12/1998", "DESCRIPCIONTRAMITE": "Cuenta de primer informe de comisión .", "ETAPDESCRIPCION": "Primer trámite constitucional", "CAMARATRAMITE": "C.Diputados"}, {"SESION": "/", "FECHA": "15/12/1998", "DESCRIPCIONTRAMITE": "Primer informe de comisión de Hacienda.", "ETAPDESCRIPCION": "Primer trámite constitucional", "CAMARATRAMITE": "C.Diputados"}, {"SESION": "28/339", "FECHA": "16/12/1998", "DESCRIPCIONTRAMITE": "Discusión general . Aprobado en general y particular a la vez", "ETAPDESCRIPCION": "Primer trámite constitucional", "CAMARATRAMITE": "C.Diputados"}, {"SESION": "/", "FECHA": "16/12/1998", "DESCRIPCIONTRAMITE": "Oficio de ley a Cámara Revisora .", "ETAPDESCRIPCION": "Primer trámite constitucional", "CAMARATRAMITE": "C.Diputados"}, {"SESION": "13/339", "FECHA": "22/12/1998", "DESCRIPCIONTRAMITE": "Cuenta de proyecto . Pasa a Comisión de Hacienda", "ETAPDESCRIPCION": "Segundo trámite constitucional", "CAMARATRAMITE": "Senado"}, {"SESION": "/", "FECHA": "22/12/1998", "DESCRIPCIONTRAMITE": "Primer informe de comisión de Hacienda.", "ETAPDESCRIPCION": "Segundo trámite constitucional", "CAMARATRAMITE": "Senado"}, {"SESION": "13/339", "FECHA": "22/12/1998", "DESCRIPCIONTRAMITE": "Cuenta de primer informe de comisión .", "ETAPDESCRIPCION": "Segundo trámite constitucional", "CAMARATRAMITE": "Senado"}, {"SESION": "13/339", "FECHA": "22/12/1998", "DESCRIPCIONTRAMITE": "Discusión general . Aprobado en general y particular sin modificaciones", "ETAPDESCRIPCION": "Segundo trámite constitucional", "CAMARATRAMITE": "Senado"}, {"SESION": "/", "FECHA": "29/12/1998", "DESCRIPCIONTRAMITE": "Oficio aprobación sin modificaciones a Cámara de Origen .", "ETAPDESCRIPCION": "Segundo trámite constitucional", "CAMARATRAMITE": "Senado"}, {"SESION": "/", "FECHA": "29/12/1998", "DESCRIPCIONTRAMITE": "Oficio de ley al Ejecutivo .", "ETAPDESCRIPCION": "Trámite finalización en Cámara de Origen", "CAMARATRAMITE": "C.Diputados"}, {"SESION": "30/339", "FECHA": "05/01/1999", "DESCRIPCIONTRAMITE": "Cuenta oficio aprobación sin modificaciones de C. Revisora .", "ETAPDESCRIPCION": "Trámite finalización en Cámara de Origen", "CAMARATRAMITE": "C.Diputados"}]}, "votaciones": null, "urgencias": {"urgencia": {"TIPO": "Discusión inmediata", "FECHAINGRESO": "10/12/1998", "FECHARETIRO": "09/01/1999", "MENSAJERETIRO": "CADUCADA"}}, "informes": {"informe": [{"FECHAINFORME": "16/12/1998", "TRAMITE": "Primer informe de comisión de Hacienda", "ETAPA": "Primer trámite constitucional", "LINK_INFORME": "http://www.senado.cl/appsenado/index.php?mo=tramitacion&ac=getDocto&iddocto=3502&tipodoc=info"}, {"FECHAINFORME": "22/12/1998", "TRAMITE": "Primer informe de comisión de Hacienda", "ETAPA": "Segundo trámite constitucional", "LINK_INFORME": "http://www.senado.cl/appsenado/index.php?mo=tramitacion&ac=getDocto&iddocto=3503&tipodoc=info"}]}, "comparados": null, "oficios": {"oficio": [{"NUMERO": "2215", "FECHA": "22/12/1998", "TRAMITE": "Oficio de ley a Cámara Revisora", "ETAPA": "Primer trámite constitucional", "TIPO": "Ley", "CAMARA": "C. Diputados", "LINK_OFICIO": "http://www.senado.cl/appsenado/index.php?mo=tramitacion&ac=getDocto&iddocto=3512&tipodoc=ofic"}, {"NUMERO": "13301", "FECHA": "29/12/1998", "TRAMITE": "Oficio aprobación sin modificaciones a Cámara de Origen", "ETAPA": "Segundo trámite constitucional", "TIPO": "Ley", "CAMARA": "Senado", "LINK_OFICIO": "http://www.senado.cl/appsenado/index.php?mo=tramitacion&ac=getDocto&iddocto=3513&tipodoc=ofic"}, {"NUMERO": "2219", "FECHA": "29/12/1998", "TRAMITE": "Oficio de ley al Ejecutivo", "ETAPA": "Trámite finalización en Cámara de Origen", "TIPO": "Ley", "CAMARA": "C. Diputados", "LINK_OFICIO": "http://www.senado.cl/appsenado/index.php?mo=tramitacion&ac=getDocto&iddocto=3514&tipodoc=ofic"}]}, "indicaciones": null, "observaciones": null, "materias": {"materia": [{"DESCRIPCION": "FUNDACIÓN TERESA DE LOS ANDES"}, {"DESCRIPCION": "IGLESIAS"}]}}}, "ID": "2275"}