{"TotalAbstenciones": "1", "Resultado": "UNANIME", "Quorum": "LEY ORGANICA CONSTITUCIONAL", "Tipo": "GENERAL", "Informe": "PRIMER INFORME", "Fecha": "2002-07-30T13:19:57", "TotalAfirmativos": "104", "TotalNegativos": "1", "Temas": ["medio_ambiente_y_bienes_nacionales", "Hacienda_y_relaciones_exteriores", "vivienda_y_urbanismo"], "Articulo": "Todas las enmiendas con excepción art. 3º, letra f); artículo 12 que pasa a ser art. 9º, art. 12, nuevo y art. 1º transitorio", "Boletin": "2296-18", "Sesion": {"Fecha": "2002-07-30T11:00:00", "Tipo": "Ordinaria", "ID": "532", "Numero": "21", "FechaTermino": "0001-01-01T00:00:00"}, "Tramite": "TERCER TRÁMITE", "ID": "1565", "TotalDispensados": "0"}