{"TotalAbstenciones": "0", "Resultado": "APROBADO", "Quorum": "QUORUM SIMPLE", "Tipo": "GENERAL", "Informe": "PRIMER INFORME", "Fecha": "2015-12-16T13:07:19", "TotalAfirmativos": "101", "TotalNegativos": "0", "Temas": [["Medio_ambiente_y_bienes_nacionales", ["urbanismo(8)", "nacionales(6)", "areas(8)", "largo(6)"]], ["Vivienda_y_urbanismo", ["urbanismo(8)", "construcciones(6)", "vivienda(14)", "vecinos(6)"]], ["Trabajo_y_prevision_social", ["iluminacion(7)", "proyecto(10)"]]], "Articulo": "", "Boletin": "9988-14", "Sesion": {"Fecha": "2015-12-16T10:37:00", "Tipo": "Ordinaria", "ID": "3294", "Numero": "106", "FechaTermino": "0001-01-01T00:00:00"}, "Tramite": "PRIMER TRÁMITE", "ID": "22685", "TotalDispensados": "0"}