{"TotalAbstenciones": "0", "Resultado": "UNANIME", "Quorum": "QUORUM SIMPLE", "Tipo": "GENERAL Y PARTICULAR", "Informe": "PRIMER INFORME", "Fecha": "2003-08-13T13:45:21", "TotalAfirmativos": "98", "TotalNegativos": "0", "Temas": [["Hacienda_y_relaciones_exteriores", ["deudas(50)", "hacienda(7)", "cuenta(10)", "financiamiento(7)", "anos(20)", "bien(9)", "cuentan(8)", "deuda(60)", "acuerdo(6)", "pago(16)", "economica(18)", "financiar(8)", "acercado(6)", "economicos(15)", "mercado(6)", "economia(10)", "economico(10)"]], ["Trabajo_y_prevision_social", ["proyecto(48)", "comisiones(7)", "nacional(11)", "encontrado(6)", "profesionales(14)", "obligacion(8)", "consejo(7)", "beneficio(14)", "gente(11)", "social(12)", "beneficios(8)", "instituciones(6)", "situacion(7)", "contado(14)", "dia(8)"]], ["Medio_ambiente_y_bienes_nacionales", ["comisiones(7)", "nacional(22)", "recursos(52)", "ano(12)", "carreras(8)", "comision(7)", "tambien(12)", "cuotas(16)", "cultura(8)", "cambio(8)", "camino(6)", "cosas(8)", "sustentable(8)", "derecho(8)"]]], "Articulo": "", "Boletin": "3314-04", "Sesion": {"Fecha": "2003-08-13T10:30:00", "Tipo": "Ordinaria", "ID": "415", "Numero": "29", "FechaTermino": "0001-01-01T00:00:00"}, "Tramite": "SEGUNDO TRÁMITE", "ID": "2639", "TotalDispensados": "0"}