{"TotalAbstenciones": "5", "Resultado": "APROBADO", "Quorum": "QUORUM SIMPLE", "Tipo": "GENERAL", "Informe": "PRIMER INFORME", "Fecha": "2019-01-10T12:50:19", "TotalAfirmativos": "112", "TotalNegativos": "0", "Temas": [["Trabajo_y_prevision_social", ["connotacion(23)", "proyecto(69)", "codigo(16)", "proyectos(10)", "indicacion(12)", "relacion(34)", "proteccion(7)", "sociales(70)", "nacional(7)", "presentacion(6)", "situacion(8)", "relaciones(11)", "investigaciones(8)", "beneficios(8)", "situaciones(9)", "acoso(7)", "social(10)", "masificacion(8)"]], ["Justicia_y_derechos_humanos", ["penal(33)", "seguridad(14)", "ciudadana(24)", "diputados(17)", "articulo(14)", "pena(12)", "grabaciones(9)", "proteccion(7)", "registros(6)", "diputado(19)", "libertad(7)", "carcel(8)", "nacional(7)", "penas(7)", "legislacion(9)", "derechos(6)", "derecho(24)"]], ["Medio_ambiente_y_bienes_nacionales", ["pareja(19)", "comision(23)", "carter(6)", "consta(6)", "medio(13)", "cambios(6)", "tambien(25)", "nacional(14)", "medios(6)", "cosas(10)", "camino(6)", "derechos(6)", "derecho(24)"]]], "Articulo": "", "Boletin": "11923-25", "Sesion": {"Fecha": "2019-01-10T10:05:16", "Tipo": "Ordinaria", "ID": "3715", "Numero": "124", "FechaTermino": "0001-01-01T00:00:00"}, "Tramite": "PRIMER TRÁMITE", "ID": "30428", "TotalDispensados": "0"}