{"TotalAbstenciones": "0", "Resultado": "UNANIME", "Quorum": "QUORUM SIMPLE", "Tipo": "GENERAL", "Informe": "PRIMER INFORME", "Fecha": "2002-12-19T12:06:00", "TotalAfirmativos": "65", "TotalNegativos": "0", "Temas": [["Trabajo_y_prevision_social", ["proyecto(12)", "recuperacion(8)", "contratos(9)", "procedimiento(10)", "constitucion(10)"]], ["Justicia_y_derechos_humanos", ["diputado(9)", "tribunales(6)", "procedimiento(10)", "derechos(8)"]], ["Medio_ambiente_y_bienes_nacionales", ["comision(14)", "rios(8)", "derechos(8)"]]], "Articulo": "", "Boletin": "2625-07", "Sesion": {"Fecha": "2002-12-19T10:30:00", "Tipo": "Ordinaria", "ID": "584", "Numero": "37", "FechaTermino": "0001-01-01T00:00:00"}, "Tramite": "SEGUNDO TRÁMITE", "ID": "1990", "TotalDispensados": "0"}