<?xml version="1.0" encoding="utf-8"?>
<Votaciones xmlns:xsi="http://www.w3.org/2001/XMLSchema-instance" xmlns:xsd="http://www.w3.org/2001/XMLSchema" xmlns="http://tempuri.org/">
  <Votacion>
    <ID>3836</ID>
    <Fecha>2004-10-20T12:28:17</Fecha>
    <Tipo Codigo="2">PARTICULAR</Tipo>
    <Resultado Codigo="1">APROBADO</Resultado>
    <Quorum Codigo="1">QUORUM SIMPLE</Quorum>
    <Sesion>
      <ID>59</ID>
      <Numero>10</Numero>
      <Fecha>2004-10-20T10:30:00</Fecha>
      <FechaTermino>0001-01-01T00:00:00</FechaTermino>
      <Tipo Codigo="60">Ordinaria</Tipo>
    </Sesion>
    <Boletin>3393-17</Boletin>
    <Articulo>Enmiendas del Senado.
</Articulo>
    <Tramite Codigo="3">TERCER TRÁMITE</Tramite>
    <Informe Codigo="1">PRIMER INFORME</Informe>
    <TotalAfirmativos>67</TotalAfirmativos>
    <TotalNegativos>0</TotalNegativos>
    <TotalAbstenciones>1</TotalAbstenciones>
    <TotalDispensados>0</TotalDispensados>
  </Votacion>
  <Votacion>
    <ID>3339</ID>
    <Fecha>2004-05-11T19:13:00</Fecha>
    <Tipo Codigo="2">PARTICULAR</Tipo>
    <Resultado Codigo="5">UNANIME</Resultado>
    <Quorum Codigo="1">QUORUM SIMPLE</Quorum>
    <Sesion>
      <ID>399</ID>
      <Numero>83</Numero>
      <Fecha>2004-05-11T16:00:00</Fecha>
      <FechaTermino>0001-01-01T00:00:00</FechaTermino>
      <Tipo Codigo="61">Especial</Tipo>
    </Sesion>
    <Boletin>3393-17</Boletin>
    <Articulo>6°, más indicación de Comisión de Hacienda</Articulo>
    <Tramite Codigo="1">PRIMER TRÁMITE</Tramite>
    <Informe Codigo="2">SEGUNDO INFORME</Informe>
    <TotalAfirmativos>90</TotalAfirmativos>
    <TotalNegativos>0</TotalNegativos>
    <TotalAbstenciones>0</TotalAbstenciones>
    <TotalDispensados>0</TotalDispensados>
  </Votacion>
  <Votacion>
    <ID>3337</ID>
    <Fecha>2004-05-11T19:12:00</Fecha>
    <Tipo Codigo="2">PARTICULAR</Tipo>
    <Resultado Codigo="5">UNANIME</Resultado>
    <Quorum Codigo="1">QUORUM SIMPLE</Quorum>
    <Sesion>
      <ID>399</ID>
      <Numero>83</Numero>
      <Fecha>2004-05-11T16:00:00</Fecha>
      <FechaTermino>0001-01-01T00:00:00</FechaTermino>
      <Tipo Codigo="61">Especial</Tipo>
    </Sesion>
    <Boletin>3393-17</Boletin>
    <Articulo>artículo 4°
</Articulo>
    <Tramite Codigo="1">PRIMER TRÁMITE</Tramite>
    <Informe Codigo="2">SEGUNDO INFORME</Informe>
    <TotalAfirmativos>87</TotalAfirmativos>
    <TotalNegativos>0</TotalNegativos>
    <TotalAbstenciones>0</TotalAbstenciones>
    <TotalDispensados>0</TotalDispensados>
  </Votacion>
  <Votacion>
    <ID>3338</ID>
    <Fecha>2004-05-11T19:12:00</Fecha>
    <Tipo Codigo="2">PARTICULAR</Tipo>
    <Resultado Codigo="5">UNANIME</Resultado>
    <Quorum Codigo="1">QUORUM SIMPLE</Quorum>
    <Sesion>
      <ID>399</ID>
      <Numero>83</Numero>
      <Fecha>2004-05-11T16:00:00</Fecha>
      <FechaTermino>0001-01-01T00:00:00</FechaTermino>
      <Tipo Codigo="61">Especial</Tipo>
    </Sesion>
    <Boletin>3393-17</Boletin>
    <Articulo>5°</Articulo>
    <Tramite Codigo="1">PRIMER TRÁMITE</Tramite>
    <Informe Codigo="2">SEGUNDO INFORME</Informe>
    <TotalAfirmativos>91</TotalAfirmativos>
    <TotalNegativos>0</TotalNegativos>
    <TotalAbstenciones>0</TotalAbstenciones>
    <TotalDispensados>0</TotalDispensados>
  </Votacion>
  <Votacion>
    <ID>3336</ID>
    <Fecha>2004-05-11T19:11:00</Fecha>
    <Tipo Codigo="2">PARTICULAR</Tipo>
    <Resultado Codigo="5">UNANIME</Resultado>
    <Quorum Codigo="1">QUORUM SIMPLE</Quorum>
    <Sesion>
      <ID>399</ID>
      <Numero>83</Numero>
      <Fecha>2004-05-11T16:00:00</Fecha>
      <FechaTermino>0001-01-01T00:00:00</FechaTermino>
      <Tipo Codigo="61">Especial</Tipo>
    </Sesion>
    <Boletin>3393-17</Boletin>
    <Articulo>1°, número 1</Articulo>
    <Tramite Codigo="1">PRIMER TRÁMITE</Tramite>
    <Informe Codigo="2">SEGUNDO INFORME</Informe>
    <TotalAfirmativos>92</TotalAfirmativos>
    <TotalNegativos>0</TotalNegativos>
    <TotalAbstenciones>0</TotalAbstenciones>
    <TotalDispensados>0</TotalDispensados>
  </Votacion>
  <Votacion>
    <ID>2967</ID>
    <Fecha>2004-01-07T12:31:19</Fecha>
    <Tipo Codigo="1">GENERAL</Tipo>
    <Resultado Codigo="5">UNANIME</Resultado>
    <Quorum Codigo="1">QUORUM SIMPLE</Quorum>
    <Sesion>
      <ID>358</ID>
      <Numero>39</Numero>
      <Fecha>2004-01-07T10:30:00</Fecha>
      <FechaTermino>0001-01-01T00:00:00</FechaTermino>
      <Tipo Codigo="60">Ordinaria</Tipo>
    </Sesion>
    <Boletin>3393-17</Boletin>
    <Articulo />
    <Tramite Codigo="1">PRIMER TRÁMITE</Tramite>
    <Informe Codigo="1">PRIMER INFORME</Informe>
    <TotalAfirmativos>77</TotalAfirmativos>
    <TotalNegativos>1</TotalNegativos>
    <TotalAbstenciones>1</TotalAbstenciones>
    <TotalDispensados>0</TotalDispensados>
  </Votacion>
</Votaciones>